xsd_validator/__init__.py
xsd_validator/__main__.py
xsd_validator/resources/com.innodata.XsdValidator.jar
xsd_validator/resources/org.eclipse.wst.xml.xpath2.processor_1.2.0.jar
xsd_validator/test/__init__.py
xsd_validator/test/test_xsd_validator.py
xsd_validator-0.0.3.dist-info/LICENSE
xsd_validator-0.0.3.dist-info/METADATA
xsd_validator-0.0.3.dist-info/WHEEL
xsd_validator-0.0.3.dist-info/top_level.txt
xsd_validator-0.0.3.dist-info/RECORD
