Metadata-Version: 2.1
Name: xsd-validator
Version: 0.0.3
Summary: Validates XML file against XSD, supporting XSD versionj 1.1
Home-page: https://github.com/innodatalabs/xsd-validator
Author: Mike Kroutikov
Author-email: mkroutikov@innodata.com
License: MIT
Platform: UNKNOWN
Classifier: Development Status :: 4 - Beta
Classifier: Intended Audience :: Developers
Classifier: Programming Language :: Python :: 3 :: Only
Classifier: Programming Language :: Python :: 3.7
Classifier: Programming Language :: Python :: 3.8
Classifier: Programming Language :: Python :: 3.9
Classifier: License :: OSI Approved :: MIT License
Classifier: Operating System :: OS Independent
Requires-Python: >=3.6
